pylava/__init__.py
pylava/__main__.py
pylava/async_mode.py
pylava/config.py
pylava/core.py
pylava/errors.py
pylava/hook.py
pylava/main.py
pylava/pytest.py
pylava/libs/__init__.py
pylava/libs/importlib.py
pylava/libs/inirama.py
pylava/lint/__init__.py
pylava/lint/extensions.py
pylava/lint/pylava_mccabe.py
pylava/lint/pylava_pycodestyle.py
pylava/lint/pylava_pydocstyle.py
pylava/lint/pylava_pyflakes.py
pylava/lint/pylava_radon.py
pylava-0.3.0.dist-info/AUTHORS.rst
pylava-0.3.0.dist-info/LICENSE.rst
pylava-0.3.0.dist-info/METADATA
pylava-0.3.0.dist-info/WHEEL
pylava-0.3.0.dist-info/entry_points.txt
pylava-0.3.0.dist-info/top_level.txt
pylava-0.3.0.dist-info/RECORD
