Metadata-Version: 1.2
Name: pylava
Version: 0.3.0
Summary: Pylava -- Code audit tool for Python
Home-page:  https://github.com/pylava/pylava
Maintainer: Susam Pal
Maintainer-email: susam@susam.in
License: MIT
Keywords: pylint,pep8,pycodestyle,pyflakes,mccabe,linter,qa,pep257,pydocstyle
Platform: Any
Classifier: Topic :: Software Development :: Libraries :: Python Modules
Classifier: Topic :: Software Development :: Quality Assurance
Classifier: Development Status :: 4 - Beta
Classifier: Environment :: Console
Classifier: Intended Audience :: Developers
Classifier: Intended Audience :: System Administrators
Classifier: License :: OSI Approved :: MIT License
Classifier: Natural Language :: English
Classifier: Natural Language :: Russian
Classifier: Programming Language :: Python :: 2
Classifier: Programming Language :: Python :: 3
Classifier: Programming Language :: Python
Classifier: Topic :: Software Development :: Code Generators
